<?xml version="1.0" encoding="UTF-8"?>
<channels>
  <channel site="hot.net.il" lang="he" xmltv_id="" site_id="335">Euronews</channel>
  <channel site="hot.net.il" lang="he" xmltv_id="" site_id="428">Sport5Gold</channel>
  <channel site="hot.net.il" lang="he" xmltv_id="" site_id="429">Sport5PlusLive</channel>
  <channel site="hot.net.il" lang="he" xmltv_id="" site_id="431">IsraelPlus</channel>
  <channel site="hot.net.il" lang="he" xmltv_id="" site_id="441">BBCWorldNews</channel>
  <channel site="hot.net.il" lang="he" xmltv_id="" site_id="443">Bloomberg</channel>
  <channel site="hot.net.il" lang="he" xmltv_id="" site_id="451">Cnn</channel>
  <channel site="hot.net.il" lang="he" xmltv_id="" site_id="461">EuroSport1</channel>
  <channel site="hot.net.il" lang="he" xmltv_id="" site_id="465">FoxNews</channel>
  <channel site="hot.net.il" lang="he" xmltv_id="" site_id="468">France24</channel>
  <channel site="hot.net.il" lang="he" xmltv_id="" site_id="477">Hot3</channel>
  <channel site="hot.net.il" lang="he" xmltv_id="" site_id="513">Junior</channel>
  <channel site="hot.net.il" lang="he" xmltv_id="" site_id="522">Mtv</channel>
  <channel site="hot.net.il" lang="he" xmltv_id="" site_id="542">SkyNews</channel>
  <channel site="hot.net.il" lang="he" xmltv_id="" site_id="544">Sport5HD</channel>
  <channel site="hot.net.il" lang="he" xmltv_id="" site_id="566">Disney</channel>
  <channel site="hot.net.il" lang="he" xmltv_id="" site_id="567">HomePlus</channel>
  <channel site="hot.net.il" lang="he" xmltv_id="" site_id="574">ShoppingChannel21</channel>
  <channel site="hot.net.il" lang="he" xmltv_id="" site_id="578">Channel24</channel>
  <channel site="hot.net.il" lang="he" xmltv_id="" site_id="579">Nick</channel>
  <channel site="hot.net.il" lang="he" xmltv_id="" site_id="580">Sport1</channel>
  <channel site="hot.net.il" lang="he" xmltv_id="" site_id="581">Sport2</channel>
  <channel site="hot.net.il" lang="he" xmltv_id="" site_id="582">Sport5</channel>
  <channel site="hot.net.il" lang="he" xmltv_id="" site_id="583">Sport5Plus</channel>
  <channel site="hot.net.il" lang="he" xmltv_id="" site_id="591">Hop</channel>
  <channel site="hot.net.il" lang="he" xmltv_id="" site_id="592">HopYaldut</channel>
  <channel site="hot.net.il" lang="he" xmltv_id="" site_id="673">EuroSport2</channel>
  <channel site="hot.net.il" lang="he" xmltv_id="" site_id="685">One1</channel>
  <channel site="hot.net.il" lang="he" xmltv_id="" site_id="710">NickJunior</channel>
  <channel site="hot.net.il" lang="he" xmltv_id="" site_id="738">Zoom</channel>
  <channel site="hot.net.il" lang="he" xmltv_id="" site_id="751">DisneyJunior</channel>
  <channel site="hot.net.il" lang="he" xmltv_id="" site_id="766">Channel20</channel>
  <channel site="hot.net.il" lang="he" xmltv_id="" site_id="771">DwNews</channel>
  <channel site="hot.net.il" lang="he" xmltv_id="" site_id="791">FoxBusiness</channel>
  <channel site="hot.net.il" lang="he" xmltv_id="" site_id="792">TeenNick</channel>
  <channel site="hot.net.il" lang="he" xmltv_id="" site_id="826">Sport3</channel>
  <channel site="hot.net.il" lang="he" xmltv_id="" site_id="828">Sport4</channel>
  <channel site="hot.net.il" lang="he" xmltv_id="" site_id="839">Kan11</channel>
  <channel site="hot.net.il" lang="he" xmltv_id="" site_id="841">Makan33</channel>
  <channel site="hot.net.il" lang="he" xmltv_id="" site_id="861">Keshet12</channel>
  <channel site="hot.net.il" lang="he" xmltv_id="" site_id="863">Reshet13</channel>
  <channel site="hot.net.il" lang="he" xmltv_id="" site_id="871">Kidz</channel>
  <channel site="hot.net.il" lang="he" xmltv_id="" site_id="907">I24English</channel>
  <channel site="hot.net.il" lang="he" xmltv_id="" site_id="912">One2</channel>
</channels>
