<?xml version="1.0" encoding="UTF-8"?>
<channels>
  <channel site="orangetv.es" lang="es" xmltv_id="" site_id="1001">La 1 HD TDT</channel>
  <channel site="orangetv.es" lang="es" xmltv_id="" site_id="1002">La 2 HD TDT</channel>
  <channel site="orangetv.es" lang="es" xmltv_id="" site_id="1007">C.Aut</channel>
  <channel site="orangetv.es" lang="es" xmltv_id="" site_id="1010">La 1 HD</channel>
  <channel site="orangetv.es" lang="es" xmltv_id="" site_id="1011">Antena 3 HD</channel>
  <channel site="orangetv.es" lang="es" xmltv_id="" site_id="1012">Cuatro HD</channel>
  <channel site="orangetv.es" lang="es" xmltv_id="" site_id="1013">Telecinco HD</channel>
  <channel site="orangetv.es" lang="es" xmltv_id="" site_id="1014">laSexta HD</channel>
  <channel site="orangetv.es" lang="es" xmltv_id="" site_id="1015">24h TDT</channel>
  <channel site="orangetv.es" lang="es" xmltv_id="" site_id="1023">M Liga de Campeones</channel>
  <channel site="orangetv.es" lang="es" xmltv_id="" site_id="1025">Paramount</channel>
  <channel site="orangetv.es" lang="es" xmltv_id="" site_id="1050">M Liga de Campeones 2</channel>
  <channel site="orangetv.es" lang="es" xmltv_id="" site_id="1051">M Liga de Campeones 3</channel>
  <channel site="orangetv.es" lang="es" xmltv_id="" site_id="1052">M Liga de Campeones 4</channel>
  <channel site="orangetv.es" lang="es" xmltv_id="" site_id="1053">M Liga de Campeones 5</channel>
  <channel site="orangetv.es" lang="es" xmltv_id="" site_id="1054">M Liga de Campeones 6</channel>
  <channel site="orangetv.es" lang="es" xmltv_id="" site_id="1055">M Liga de Campeones 7</channel>
  <channel site="orangetv.es" lang="es" xmltv_id="" site_id="1056">M Liga de Campeones 8</channel>
  <channel site="orangetv.es" lang="es" xmltv_id="" site_id="1057">M LALIGATV 3</channel>
  <channel site="orangetv.es" lang="es" xmltv_id="" site_id="1058">M LALIGATV 4</channel>
  <channel site="orangetv.es" lang="es" xmltv_id="" site_id="1062">La 2 HD</channel>
  <channel site="orangetv.es" lang="es" xmltv_id="" site_id="1063">TDP HD</channel>
  <channel site="orangetv.es" lang="es" xmltv_id="" site_id="1064">Clan HD</channel>
  <channel site="orangetv.es" lang="es" xmltv_id="" site_id="1071">Autonómico</channel>
  <channel site="orangetv.es" lang="es" xmltv_id="" site_id="1092">Autonómico 2</channel>
  <channel site="orangetv.es" lang="es" xmltv_id="" site_id="1093">Autonómico 3</channel>
  <channel site="orangetv.es" lang="es" xmltv_id="" site_id="1094">Autonómico 4</channel>
  <channel site="orangetv.es" lang="es" xmltv_id="" site_id="1096">M Liga de Campeones 10</channel>
  <channel site="orangetv.es" lang="es" xmltv_id="" site_id="1097">M Liga de Campeones 11</channel>
  <channel site="orangetv.es" lang="es" xmltv_id="" site_id="1098">M Liga de Campeones 12</channel>
  <channel site="orangetv.es" lang="es" xmltv_id="" site_id="1099">M Liga de Campeones 13</channel>
  <channel site="orangetv.es" lang="es" xmltv_id="" site_id="1103">Local 1</channel>
  <channel site="orangetv.es" lang="es" xmltv_id="" site_id="1104">Local 2</channel>
  <channel site="orangetv.es" lang="es" xmltv_id="" site_id="1105">Local 3</channel>
  <channel site="orangetv.es" lang="es" xmltv_id="" site_id="1106">Local 4</channel>
  <channel site="orangetv.es" lang="es" xmltv_id="" site_id="2002">TV Ceuta</channel>
  <channel site="orangetv.es" lang="es" xmltv_id="" site_id="2005">CEX</channel>
  <channel site="orangetv.es" lang="es" xmltv_id="" site_id="2007">Telemadrid HD</channel>
  <channel site="orangetv.es" lang="es" xmltv_id="" site_id="2008">TV3 HD</channel>
  <channel site="orangetv.es" lang="es" xmltv_id="" site_id="2009">TPA HD</channel>
  <channel site="orangetv.es" lang="es" xmltv_id="" site_id="2010">ATV HD</channel>
  <channel site="orangetv.es" lang="es" xmltv_id="" site_id="2011">7RM HD</channel>
  <channel site="orangetv.es" lang="es" xmltv_id="" site_id="2012">CMTV HD</channel>
  <channel site="orangetv.es" lang="es" xmltv_id="" site_id="2013">IB3 HD</channel>
  <channel site="orangetv.es" lang="es" xmltv_id="" site_id="2014">ETB1 HD</channel>
  <channel site="orangetv.es" lang="es" xmltv_id="" site_id="2016">A7</channel>
  <channel site="orangetv.es" lang="es" xmltv_id="" site_id="2022">CanalSur 2</channel>
  <channel site="orangetv.es" lang="es" xmltv_id="" site_id="2023">ETB2 Navarra</channel>
  <channel site="orangetv.es" lang="es" xmltv_id="" site_id="2026">A8</channel>
  <channel site="orangetv.es" lang="es" xmltv_id="" site_id="2027">Super 3/33</channel>
  <channel site="orangetv.es" lang="es" xmltv_id="" site_id="2028">La 8</channel>
  <channel site="orangetv.es" lang="es" xmltv_id="" site_id="2029">Navarra TV2</channel>
  <channel site="orangetv.es" lang="es" xmltv_id="" site_id="2030">Canal 4</channel>
  <channel site="orangetv.es" lang="es" xmltv_id="" site_id="2031">Andalucía TV</channel>
  <channel site="orangetv.es" lang="es" xmltv_id="" site_id="2032">ETB3</channel>
  <channel site="orangetv.es" lang="es" xmltv_id="" site_id="2033">Vtelevisión</channel>
  <channel site="orangetv.es" lang="es" xmltv_id="" site_id="2035">TV3 CAT</channel>
  <channel site="orangetv.es" lang="es" xmltv_id="" site_id="2036">ETB1 Navarra</channel>
  <channel site="orangetv.es" lang="es" xmltv_id="" site_id="2037">ETB4</channel>
  <channel site="orangetv.es" lang="es" xmltv_id="" site_id="2038">Esport3</channel>
  <channel site="orangetv.es" lang="es" xmltv_id="" site_id="2041">8TV</channel>
  <channel site="orangetv.es" lang="es" xmltv_id="" site_id="2042">8 Madrid</channel>
  <channel site="orangetv.es" lang="es" xmltv_id="" site_id="2044">ETB3 Navarra</channel>
  <channel site="orangetv.es" lang="es" xmltv_id="" site_id="2045">ETB2 HD</channel>
  <channel site="orangetv.es" lang="es" xmltv_id="" site_id="2046">HIT TV</channel>
  <channel site="orangetv.es" lang="es" xmltv_id="" site_id="2047">Barcelona TV</channel>
  <channel site="orangetv.es" lang="es" xmltv_id="" site_id="2049">IB3 Global</channel>
  <channel site="orangetv.es" lang="es" xmltv_id="" site_id="2050">3/24</channel>
  <channel site="orangetv.es" lang="es" xmltv_id="" site_id="2051">CanalSur TV HD</channel>
  <channel site="orangetv.es" lang="es" xmltv_id="" site_id="2052">TVG HD</channel>
  <channel site="orangetv.es" lang="es" xmltv_id="" site_id="2053">TVG2 HD</channel>
  <channel site="orangetv.es" lang="es" xmltv_id="" site_id="2054">CYLTV HD</channel>
  <channel site="orangetv.es" lang="es" xmltv_id="" site_id="2055">TVR HD</channel>
  <channel site="orangetv.es" lang="es" xmltv_id="" site_id="2057">A punt HD</channel>
  <channel site="orangetv.es" lang="es" xmltv_id="" site_id="2059">RTV Canaria HD</channel>
  <channel site="orangetv.es" lang="es" xmltv_id="" site_id="2060">Navarra TV HD</channel>
  <channel site="orangetv.es" lang="es" xmltv_id="" site_id="2061">La otra HD</channel>
  <channel site="orangetv.es" lang="es" xmltv_id="" site_id="2062">8 Mediterraneo</channel>
  <channel site="orangetv.es" lang="es" xmltv_id="" site_id="2063">Bom Cine</channel>
  <channel site="orangetv.es" lang="es" xmltv_id="" site_id="2064">C33</channel>
  <channel site="orangetv.es" lang="es" xmltv_id="" site_id="2065">7TV Andalucia</channel>
  <channel site="orangetv.es" lang="es" xmltv_id="" site_id="2067">TV Castellon</channel>
  <channel site="orangetv.es" lang="es" xmltv_id="" site_id="2068">Televigo</channel>
  <channel site="orangetv.es" lang="es" xmltv_id="" site_id="2069">Valencia Televisio</channel>
  <channel site="orangetv.es" lang="es" xmltv_id="" site_id="2070">Levante TV</channel>
  <channel site="orangetv.es" lang="es" xmltv_id="" site_id="2071">TVV</channel>
  <channel site="orangetv.es" lang="es" xmltv_id="" site_id="2081">SEVILLA FC Televisión</channel>
  <channel site="orangetv.es" lang="es" xmltv_id="" site_id="11001">STAR Channel</channel>
  <channel site="orangetv.es" lang="es" xmltv_id="" site_id="11002">AXN</channel>
  <channel site="orangetv.es" lang="es" xmltv_id="" site_id="11003">Calle 13</channel>
  <channel site="orangetv.es" lang="es" xmltv_id="" site_id="11004">SYFY</channel>
  <channel site="orangetv.es" lang="es" xmltv_id="" site_id="11005">ComedyCentr</channel>
  <channel site="orangetv.es" lang="es" xmltv_id="" site_id="11007">Warner TV</channel>
  <channel site="orangetv.es" lang="es" xmltv_id="" site_id="11008">AXNMovies</channel>
  <channel site="orangetv.es" lang="es" xmltv_id="" site_id="11010">C Hollywood</channel>
  <channel site="orangetv.es" lang="es" xmltv_id="" site_id="11011">AMC</channel>
  <channel site="orangetv.es" lang="es" xmltv_id="" site_id="11013">M LALIGATV</channel>
  <channel site="orangetv.es" lang="es" xmltv_id="" site_id="11018">Odisea</channel>
  <channel site="orangetv.es" lang="es" xmltv_id="" site_id="11020">CanalCocina</channel>
  <channel site="orangetv.es" lang="es" xmltv_id="" site_id="11026">M LALIGATV 2</channel>
  <channel site="orangetv.es" lang="es" xmltv_id="" site_id="11030">M Copa del Rey</channel>
  <channel site="orangetv.es" lang="es" xmltv_id="" site_id="11031">GOL PLAY</channel>
  <channel site="orangetv.es" lang="es" xmltv_id="" site_id="11035">Eurosport 1</channel>
  <channel site="orangetv.es" lang="es" xmltv_id="" site_id="11036">M Liga de Campeones 9</channel>
  <channel site="orangetv.es" lang="es" xmltv_id="" site_id="11043">M LALIGATV UHD</channel>
  <channel site="orangetv.es" lang="es" xmltv_id="" site_id="11059">Eurosport 2</channel>
  <channel site="orangetv.es" lang="es" xmltv_id="" site_id="11060">Festival 4K</channel>
  <channel site="orangetv.es" lang="es" xmltv_id="" site_id="11077">DAZN LALIGA</channel>
  <channel site="orangetv.es" lang="es" xmltv_id="" site_id="11080">DAZN LALIGA 2</channel>
  <channel site="orangetv.es" lang="es" xmltv_id="" site_id="11083">LALIGATV HYPERMOTION</channel>
  <channel site="orangetv.es" lang="es" xmltv_id="" site_id="11084">LALIGATV HYPERMOTION 2</channel>
  <channel site="orangetv.es" lang="es" xmltv_id="" site_id="11085">LALIGATV HYPERMOTION 3</channel>
  <channel site="orangetv.es" lang="es" xmltv_id="" site_id="50000">Prueba IPTV</channel>
</channels>
